burrow_cli/__init__.py
burrow_cli/main.py
burrow_cli-0.1.11.dist-info/METADATA
burrow_cli-0.1.11.dist-info/WHEEL
burrow_cli-0.1.11.dist-info/entry_points.txt
burrow_cli-0.1.11.dist-info/RECORD
