Metadata-Version: 2.1
Name: burrow-cli
Version: 0.1.11
Summary: Burrow command line app, you can launch a fractional GPU contaienr with this app, and share a link of the container to your friends, you and your friends can work colloratively together
Author: Vurtne Saerdna
Author-email: vurtnesaerdna@gmail.com
Requires-Python: >=3.9.0,<4.0.0
Classifier: Programming Language :: Python :: 3
Classifier: Programming Language :: Python :: 3.9
Classifier: Programming Language :: Python :: 3.10
Classifier: Programming Language :: Python :: 3.11
Classifier: Programming Language :: Python :: 3.12
Requires-Dist: docker (>=7.0.0,<8.0.0)
Requires-Dist: requests (==2.31.0)
Requires-Dist: typer[all] (>=0.12.3,<0.13.0)
